odoo/addons/repair_type_sequence/README.rst
odoo/addons/repair_type_sequence/__init__.py
odoo/addons/repair_type_sequence/__manifest__.py
odoo/addons/repair_type_sequence/i18n/it.po
odoo/addons/repair_type_sequence/i18n/repair_type_sequence.pot
odoo/addons/repair_type_sequence/models/__init__.py
odoo/addons/repair_type_sequence/models/repair_order.py
odoo/addons/repair_type_sequence/models/repair_type.py
odoo/addons/repair_type_sequence/readme/CONTRIBUTORS.rst
odoo/addons/repair_type_sequence/readme/DESCRIPTION.rst
odoo/addons/repair_type_sequence/static/description/icon.png
odoo/addons/repair_type_sequence/static/description/index.html
odoo/addons/repair_type_sequence/tests/__init__.py
odoo/addons/repair_type_sequence/tests/test_repair_type.py
odoo/addons/repair_type_sequence/views/repair_type_views.xml
odoo_addon_repair_type_sequence-16.0.1.0.0.3.dist-info/METADATA
odoo_addon_repair_type_sequence-16.0.1.0.0.3.dist-info/WHEEL
odoo_addon_repair_type_sequence-16.0.1.0.0.3.dist-info/top_level.txt
odoo_addon_repair_type_sequence-16.0.1.0.0.3.dist-info/RECORD
